daisytuner/__init__.py
daisytuner/benchmarking/__init__.py
daisytuner/benchmarking/benchmark.py
daisytuner/benchmarking/cpu_benchmark.py
daisytuner/benchmarking/gpu_benchmark.py
daisytuner/cli/__init__.py
daisytuner/data/3rdParty/LICENSE_Daisytuner
daisytuner/data/3rdParty/README.md
daisytuner/device_mapping/__init__.py
daisytuner/device_mapping/device_mapper.py
daisytuner/embeddings/__init__.py
daisytuner/embeddings/map_nest.py
daisytuner/embeddings/map_nest_model.py
daisytuner/library/__init__.py
daisytuner/library/blas/__init__.py
daisytuner/library/blas/gemm.py
daisytuner/library/blas/gemv.py
daisytuner/library/blas/syr2k.py
daisytuner/library/blas/syrk.py
daisytuner/library/sparse/__init__.py
daisytuner/library/sparse/csrmm.py
daisytuner/library/sparse/csrmv.py
daisytuner/normalization/__init__.py
daisytuner/normalization/map_compact_form.py
daisytuner/normalization/map_expanded_form.py
daisytuner/normalization/map_inlining.py
daisytuner/normalization/maximal_map_fission.py
daisytuner/normalization/stride_minimization.py
daisytuner/pipelines/__init__.py
daisytuner/pipelines/transfer_tuning_pipeline.py
daisytuner/profiling/__init__.py
daisytuner/profiling/helpers.py
daisytuner/profiling/likwid_helpers.py
daisytuner/profiling/performance_counters.py
daisytuner/profiling/metrics/__init__.py
daisytuner/profiling/metrics/compund_metric.py
daisytuner/profiling/metrics/metric.py
daisytuner/profiling/metrics/metrics_factory.py
daisytuner/profiling/metrics/arm64fx/__init__.py
daisytuner/profiling/metrics/arm64fx/branch_misprediction_ratio.py
daisytuner/profiling/metrics/arm64fx/branch_rate.py
daisytuner/profiling/metrics/arm64fx/branches.py
daisytuner/profiling/metrics/arm64fx/cycles.py
daisytuner/profiling/metrics/arm64fx/flop.py
daisytuner/profiling/metrics/arm64fx/flops.py
daisytuner/profiling/metrics/arm64fx/instructions.py
daisytuner/profiling/metrics/arm64fx/instructions_per_cycle.py
daisytuner/profiling/metrics/arm64fx/l2_bandwidth.py
daisytuner_sdk-0.0.4.dist-info/LICENSE
daisytuner_sdk-0.0.4.dist-info/METADATA
daisytuner_sdk-0.0.4.dist-info/WHEEL
daisytuner_sdk-0.0.4.dist-info/entry_points.txt
daisytuner_sdk-0.0.4.dist-info/top_level.txt
daisytuner_sdk-0.0.4.dist-info/RECORD
